setup.py
bootconfig/__init__.py
bootconfig/config.py
bootconfig/configserver.py
bootconfig/device.py
bootconfig/init.py
bootconfig/serial.py
bootconfig/service.py
bootconfig/wifi.py
micropython_bootconfig.egg-info/PKG-INFO
micropython_bootconfig.egg-info/SOURCES.txt
micropython_bootconfig.egg-info/dependency_links.txt
micropython_bootconfig.egg-info/top_level.txt
micropython_bootconfig.egg-info/zip-safe