Metadata-Version: 1.0
Name: micropython-bootconfig
Version: 0.0.22
Summary: Service to allow configuring a micropython board
Home-page: https://github.com/dhubbard/micropython-bootconfig
Author: Dwight Hubbard
Author-email: dwight@dwighthubbard.com
License: MIT
Platform: UNKNOWN
